flasgger/__init__.py
flasgger/base.py
flasgger/example_app.py
flasgger/example_validation.py
flasgger/simple_test.py
flasgger/username_definitions.yml
flasgger/utils.py
flasgger/swaggerui/index.html
flasgger/swaggerui/o2c.html
flasgger/swaggerui/swagger-ui.js
flasgger/swaggerui/swagger-ui.min.js
flasgger/swaggerui/swagger.json
flasgger/swaggerui/swagger.yml
flasgger/swaggerui/css/api-explorer.css
flasgger/swaggerui/css/index.css
flasgger/swaggerui/css/print.css
flasgger/swaggerui/css/reset.css
flasgger/swaggerui/css/screen.css
flasgger/swaggerui/css/standalone.css
flasgger/swaggerui/css/typography.css
flasgger/swaggerui/fonts/droid-sans-v6-latin-700.eot
flasgger/swaggerui/fonts/droid-sans-v6-latin-700.svg
flasgger/swaggerui/fonts/droid-sans-v6-latin-700.ttf
flasgger/swaggerui/fonts/droid-sans-v6-latin-700.woff
flasgger/swaggerui/fonts/droid-sans-v6-latin-700.woff2
flasgger/swaggerui/fonts/droid-sans-v6-latin-regular.eot
flasgger/swaggerui/fonts/droid-sans-v6-latin-regular.svg
flasgger/swaggerui/fonts/droid-sans-v6-latin-regular.ttf
flasgger/swaggerui/fonts/droid-sans-v6-latin-regular.woff
flasgger/swaggerui/fonts/droid-sans-v6-latin-regular.woff2
flasgger/swaggerui/images/Swagger_explorer.png
flasgger/swaggerui/images/Swagger_explorer_min.png
flasgger/swaggerui/images/explorer_icons.png
flasgger/swaggerui/images/favicon-16x16.png
flasgger/swaggerui/images/favicon-32x32.png
flasgger/swaggerui/images/favicon.ico
flasgger/swaggerui/images/json_editor_integration.png
flasgger/swaggerui/images/logo_small.png
flasgger/swaggerui/images/pet_store_api.png
flasgger/swaggerui/images/senodio.png
flasgger/swaggerui/images/throbber.gif
flasgger/swaggerui/images/wordnik_api.png
flasgger/swaggerui/vendor/backbone-min.js
flasgger/swaggerui/vendor/bootstrap.min.js
flasgger/swaggerui/vendor/handlebars-2.0.0.js
flasgger/swaggerui/vendor/highlight.7.3.pack.js
flasgger/swaggerui/vendor/jquery-1.8.0.min.js
flasgger/swaggerui/vendor/jquery.ba-bbq.min.js
flasgger_TheodoFork-0.5.14.dist-info/LICENSE
flasgger_TheodoFork-0.5.14.dist-info/METADATA
flasgger_TheodoFork-0.5.14.dist-info/WHEEL
flasgger_TheodoFork-0.5.14.dist-info/top_level.txt
flasgger_TheodoFork-0.5.14.dist-info/RECORD
