Metadata-Version: 2.1
Name: flasgger-TheodoFork
Version: 0.5.14
Summary: Extract swagger specs from your flask project
Home-page: https://github.com/theodo/flasgger/
Author: Bruno Rocha
Author-email: rochacbruno@gmail.com
License: MIT
Platform: any
License-File: LICENSE
Requires-Dist: Flask (>=0.10)
Requires-Dist: PyYAML (==5.4.1)
Requires-Dist: jsonschema (>=2.5.1)
Requires-Dist: mistune
